full_adder.v
`ifndef FULL_ADDER_V
`define FULL_ADDER_V

// 1 bit full adder
module full_adder(
    input i_a,
    input i_b,
    input i_cin,
    output o_result,
    output o_cout);

    assign o_result = i_a ^ i_b ^ i_cin;
    assign o_cout = (i_a & i_b) | (i_a & i_cin) | (i_b & i_cin);
endmodule

`endif

full_adder.test.v
`include "full_adder.v"

`ifndef TESTS
`define TESTS 8
`endif

module test;

    // Inputs
    reg a;
    reg b;
    reg cin;

    // Outputs
    wire result;
    wire cout;

    integer i;

    // Instantiate the FA module
    full_adder uut(
        .i_a(a),
        .i_b(b),
        .i_cin(cin),
        .o_result(result),
        .o_cout(cout)
    );

    initial begin
        $dumpfile("dump.vcd");
        $dumpvars;
        a = 0;
        b = 0;
        cin = 0;
    end

    always @ (a, b, cin)
    begin
        for (i = 0; i < `TESTS; i = i+1)
            #10 {a,b,cin} = i; // Set a,b,cin to binary representation of i

        #10 $finish;
    end
endmodule

dump.vcd
$date
	Sun Feb 28 00:43:49 2016
$end
$version
	Icarus Verilog
$end
$timescale
	1s
$end
$scope module test $end
$var wire 1 ! result $end
$var wire 1 " cout $end
$var reg 1 # a $end
$var reg 1 $ b $end
$var reg 1 % cin $end
$var integer 32 & i [31:0] $end
$scope module uut $end
$var wire 1 # i_a $end
$var wire 1 $ i_b $end
$var wire 1 % i_cin $end
$var wire 1 " o_cout $end
$var wire 1 ! o_result $end
$upscope $end
$upscope $end
$enddefinitions $end
#0
$dumpvars
b0 &
0%
0$
0#
0"
0!
$end
#10
b1 &
#20
1!
b10 &
1%
#30
1!
b11 &
1$
0%
#40
1"
0!
b100 &
1%
#50
0"
1!
b101 &
1#
0$
0%
#60
1"
0!
b110 &
1%
#70
0!
b111 &
1$
0%
#80
1!
b1000 &
1%
